syft_datasets/__init__.py
syft_datasets/py.typed
syft_datasets-0.2.0.dist-info/METADATA
syft_datasets-0.2.0.dist-info/WHEEL
syft_datasets-0.2.0.dist-info/licenses/LICENSE
syft_datasets-0.2.0.dist-info/RECORD
