Metadata-Version: 2.4
Name: syft-datasets
Version: 0.2.0
Summary: Interactive dataset discovery and management for SyftBox applications with beautiful Jupyter UI and OpenAI-compatible chat interface
Project-URL: Homepage, https://github.com/OpenMined/syft-datasets
Project-URL: Documentation, https://github.com/OpenMined/syft-datasets#readme
Project-URL: Repository, https://github.com/OpenMined/syft-datasets.git
Project-URL: Bug Tracker, https://github.com/OpenMined/syft-datasets/issues
Author-email: OpenMined <info@openmined.org>
License: Apache-2.0
License-File: LICENSE
Keywords: data-science,datasets,federated-learning,jupyter,privacy,syft
Classifier: Development Status :: 4 - Beta
Classifier: Intended Audience :: Developers
Classifier: Intended Audience :: Science/Research
Classifier: License :: OSI Approved :: Apache Software License
Classifier: Programming Language :: Python :: 3
Classifier: Programming Language :: Python :: 3.9
Classifier: Programming Language :: Python :: 3.10
Classifier: Programming Language :: Python :: 3.11
Classifier: Programming Language :: Python :: 3.12
Classifier: Topic :: Scientific/Engineering :: Artificial Intelligence
Classifier: Topic :: Software Development :: Libraries :: Python Modules
Requires-Python: >=3.9
Requires-Dist: pandas>=1.3.0
Requires-Dist: requests>=2.25.0
Requires-Dist: syft-core>=0.2.0
Requires-Dist: syft-rds>=0.1.0
Requires-Dist: tabulate>=0.9.0
